{"name": "bonus2", "architecture_spec_path": "hardware_specs/generalSpec.json", "instructions": [{"type": "init", "id": 0, "begin_time": 0, "end_time": 0, "init_locs": [[0, 0, 0, 16], [1, 0, 0, 14], [2, 0, 0, 13], [3, 0, 0, 15], [4, 0, 0, 11], [5, 0, 0, 12], [6, 0, 0, 9], [7, 0, 0, 10], [8, 0, 0, 8], [9, 0, 0, 5], [10, 0, 0, 6], [11, 0, 0, 4], [12, 0, 0, 0], [13, 0, 0, 7], [14, 0, 0, 3], [15, 0, 0, 1], [16, 0, 0, 2]]}, {"type": "1qGate", "unitary": "u3", "id": 1, "locs": [[0, 0, 0, 16], [1, 0, 0, 14], [4, 0, 0, 11], [5, 0, 0, 12], [6, 0, 0, 9], [7, 0, 0, 10], [9, 0, 0, 5], [10, 0, 0, 6], [11, 0, 0, 4], [12, 0, 0, 0], [13, 0, 0, 7], [14, 0, 0, 3], [16, 0, 0, 2]], "gates": [{"name": "u3", "q": 0, "params": [4.71238898038469, 0.0, 0.0]}, {"name": "u3", "q": 1, "params": [1.5707963267948966, 0.0, 0.0]}, {"name": "u3", "q": 4, "params": [1.5707963267948966, 0.0, 0.0]}, {"name": "u3", "q": 5, "params": [4.71238898038469, 0.0, 0.0]}, {"name": "u3", "q": 6, "params": [1.5707963267948966, 0.0, 0.0]}, {"name": "u3", "q": 7, "params": [1.5707963267948966, 0.0, 0.0]}, {"name": "u3", "q": 9, "params": [1.5707963267948966, 0.0, 0.0]}, {"name": "u3", "q": 10, "params": [1.5707963267948966, 0.0, 0.0]}, {"name": "u3", "q": 11, "params": [4.71238898038469, 0.0, 0.0]}, {"name": "u3", "q": 12, "params": [1.5707963267948966, 0.0, 0.0]}, {"name": "u3", "q": 13, "params": [1.5707963267948966, 0.0, 0.0]}, {"name": "u3", "q": 14, "params": [1.5707963267948966, 0.0, 0.0]}, {"name": "u3", "q": 16, "params": [1.5707963267948966, 0.0, 0.0]}], "dependency": {"qubit": [0]}, "params_for_all_qubits": [[4.71238898038469, 0.0, 0.0], [1.5707963267948966, 0.0, 0.0], [1.5707963267948966, 0.0, 0.0], [4.71238898038469, 0.0, 0.0], [1.5707963267948966, 0.0, 0.0], [1.5707963267948966, 0.0, 0.0], [1.5707963267948966, 0.0, 0.0], [1.5707963267948966, 0.0, 0.0], [4.71238898038469, 0.0, 0.0], [1.5707963267948966, 0.0, 0.0], [1.5707963267948966, 0.0, 0.0], [1.5707963267948966, 0.0, 0.0], [1.5707963267948966, 0.0, 0.0]], "begin_time": 0, "end_time": 676}, {"type": "rearrangeJob", "id": 2, "aod_id": 0, "aod_qubits": [0, 3, 4, 7, 8, 9, 14, 15], "begin_locs": [[0, 0, 0, 16], [3, 0, 0, 15], [4, 0, 0, 11], [7, 0, 0, 10], [8, 0, 0, 8], [9, 0, 0, 5], [14, 0, 0, 3], [15, 0, 0, 1]], "end_locs": [[0, 2, 0, 8], [3, 1, 0, 8], [4, 2, 0, 6], [7, 1, 0, 6], [8, 1, 0, 5], [9, 1, 0, 4], [14, 1, 0, 2], [15, 1, 0, 1]], "dependency": {"qubit": [0, 1], "site": [], "aod": 0}, "insts": [{"type": "activate", "row_id": [0], "row_y": [10], "row_loc": [[0, 0]], "col_id": [7, 6, 5, 4, 3, 2, 1, 0], "col_x": [80, 75, 55, 50, 40, 25, 15, 5], "col_loc": [[0, 16], [0, 15], [0, 11], [0, 10], [0, 8], [0, 5], [0, 3], [0, 1]], "id": 0, "begin_time": 676, "end_time": 691}, {"type": "move:big", "move_type": "big", "row_id": [0], "row_y_begin": [10], "row_y_end": [0], "row_loc_begin": [[0, 0]], "row_loc_end": [[2, 0]], "col_id": [7, 6, 5, 4, 3, 2, 1, 0], "col_x_begin": [80, 75, 55, 50, 40, 25, 15, 5], "col_x_end": [82, 80, 62, 60, 50, 40, 20, 10], "col_loc_begin": [[0, 16], [0, 15], [0, 11], [0, 10], [0, 8], [0, 5], [0, 3], [0, 1]], "col_loc_end": [[2, 8], [1, 8], [2, 6], [1, 6], [1, 5], [1, 4], [1, 2], [1, 1]], "begin_coord": [[{"id": 0, "x": 80, "y": 10}, {"id": 3, "x": 75, "y": 10}, {"id": 4, "x": 55, "y": 10}, {"id": 7, "x": 50, "y": 10}, {"id": 8, "x": 40, "y": 10}, {"id": 9, "x": 25, "y": 10}, {"id": 14, "x": 15, "y": 10}, {"id": 15, "x": 5, "y": 10}]], "end_coord": [[{"id": 0, "x": 82, "y": 0}, {"id": 3, "x": 80, "y": 0}, {"id": 4, "x": 62, "y": 0}, {"id": 7, "x": 60, "y": 0}, {"id": 8, "x": 50, "y": 0}, {"id": 9, "x": 40, "y": 0}, {"id": 14, "x": 20, "y": 0}, {"id": 15, "x": 10, "y": 0}]], "id": 1, "begin_time": 691, "end_time": 771.966337286374}, {"type": "deactivate", "row_id": [0], "col_id": [0, 1, 2, 3, 4, 5, 6, 7], "id": 2, "begin_time": 771.966337286374, "end_time": 786.966337286374}], "begin_time": 676, "end_time": 786.966337286374}, {"type": "rearrangeJob", "id": 3, "aod_id": 1, "aod_qubits": [10, 11, 5, 6], "begin_locs": [[10, 0, 0, 6], [11, 0, 0, 4], [5, 0, 0, 12], [6, 0, 0, 9]], "end_locs": [[10, 2, 0, 2], [11, 2, 0, 1], [5, 2, 0, 5], [6, 2, 0, 4]], "dependency": {"qubit": [1], "site": [], "aod": 0}, "insts": [{"type": "activate", "row_id": [0], "row_y": [10], "row_loc": [[0, 0]], "col_id": [1, 0, 3, 2], "col_x": [30, 20, 60, 45], "col_loc": [[0, 6], [0, 4], [0, 12], [0, 9]], "id": 0, "begin_time": 676, "end_time": 691}, {"type": "move:big", "move_type": "big", "row_id": [0], "row_y_begin": [10], "row_y_end": [0], "row_loc_begin": [[0, 0]], "row_loc_end": [[2, 0]], "col_id": [1, 0, 3, 2], "col_x_begin": [30, 20, 60, 45], "col_x_end": [22, 12, 52, 42], "col_loc_begin": [[0, 6], [0, 4], [0, 12], [0, 9]], "col_loc_end": [[2, 2], [2, 1], [2, 5], [2, 4]], "begin_coord": [[{"id": 10, "x": 30, "y": 10}, {"id": 11, "x": 20, "y": 10}, {"id": 5, "x": 60, "y": 10}, {"id": 6, "x": 45, "y": 10}]], "end_coord": [[{"id": 10, "x": 22, "y": 0}, {"id": 11, "x": 12, "y": 0}, {"id": 5, "x": 52, "y": 0}, {"id": 6, "x": 42, "y": 0}]], "id": 1, "begin_time": 691, "end_time": 759.2408794435116}, {"type": "deactivate", "row_id": [0], "col_id": [0, 1, 2, 3], "id": 2, "begin_time": 759.2408794435116, "end_time": 774.2408794435116}], "begin_time": 676, "end_time": 774.2408794435116}, {"type": "rydberg", "id": 4, "zone_id": 0, "gates": [{"id": 0, "q0": 0, "q1": 3}, {"id": 2, "q0": 4, "q1": 7}, {"id": 4, "q0": 5, "q1": 8}, {"id": 8, "q0": 6, "q1": 9}, {"id": 10, "q0": 10, "q1": 14}, {"id": 16, "q0": 11, "q1": 15}], "dependency": {"qubit": [2, 3], "rydberg": 0}, "begin_time": 786.966337286374, "end_time": 787.326337286374}, {"type": "1qGate", "unitary": "u3", "id": 5, "locs": [[3, 1, 0, 8], [4, 2, 0, 6], [7, 1, 0, 6], [8, 1, 0, 5], [6, 2, 0, 4], [9, 1, 0, 4], [10, 2, 0, 2], [14, 1, 0, 2], [15, 1, 0, 1]], "gates": [{"name": "u3", "q": 3, "params": [4.71238898038469, 0.0, 0.0]}, {"name": "u3", "q": 4, "params": [3.141592653589793, 0.0, 0.0]}, {"name": "u3", "q": 7, "params": [1.5707963267948966, 3.141592653589793, 0.0]}, {"name": "u3", "q": 8, "params": [4.71238898038469, 0.0, 0.0]}, {"name": "u3", "q": 6, "params": [3.141592653589793, 0.0, 0.0]}, {"name": "u3", "q": 9, "params": [1.5707963267948966, 3.141592653589793, 0.0]}, {"name": "u3", "q": 10, "params": [3.141592653589793, 0.0, 0.0]}, {"name": "u3", "q": 14, "params": [1.5707963267948966, 3.141592653589793, 0.0]}, {"name": "u3", "q": 15, "params": [1.5707963267948966, 0.0, 0.0]}], "dependency": {"qubit": [4]}, "params_for_all_qubits": [[4.71238898038469, 0.0, 0.0], [3.141592653589793, 0.0, 0.0], [1.5707963267948966, 3.141592653589793, 0.0], [4.71238898038469, 0.0, 0.0], [3.141592653589793, 0.0, 0.0], [1.5707963267948966, 3.141592653589793, 0.0], [3.141592653589793, 0.0, 0.0], [1.5707963267948966, 3.141592653589793, 0.0], [1.5707963267948966, 0.0, 0.0]], "begin_time": 787.326337286374, "end_time": 1255.326337286374}, {"type": "rearrangeJob", "id": 6, "aod_id": 1, "aod_qubits": [3, 7, 8, 9, 14, 15], "begin_locs": [[3, 1, 0, 8], [7, 1, 0, 6], [8, 1, 0, 5], [9, 1, 0, 4], [14, 1, 0, 2], [15, 1, 0, 1]], "end_locs": [[3, 0, 0, 16], [7, 0, 0, 12], [8, 0, 0, 10], [9, 0, 0, 8], [14, 0, 0, 4], [15, 0, 0, 1]], "dependency": {"qubit": [5], "site": [2, 3], "aod": 3}, "insts": [{"type": "activate", "row_id": [0], "row_y": [0], "row_loc": [[1, 0]], "col_id": [5, 4, 3, 2, 1, 0], "col_x": [80, 60, 50, 40, 20, 10], "col_loc": [[1, 8], [1, 6], [1, 5], [1, 4], [1, 2], [1, 1]], "id": 0, "begin_time": 1255.326337286374, "end_time": 1270.326337286374}, {"type": "move:big", "move_type": "big", "row_id": [0], "row_y_begin": [0], "row_y_end": [10], "row_loc_begin": [[1, 0]], "row_loc_end": [[0, 0]], "col_id": [5, 4, 3, 2, 1, 0], "col_x_begin": [80, 60, 50, 40, 20, 10], "col_x_end": [80, 60, 50, 40, 20, 5], "col_loc_begin": [[1, 8], [1, 6], [1, 5], [1, 4], [1, 2], [1, 1]], "col_loc_end": [[0, 16], [0, 12], [0, 10], [0, 8], [0, 4], [0, 1]], "begin_coord": [[{"id": 3, "x": 80, "y": 0}, {"id": 7, "x": 60, "y": 0}, {"id": 8, "x": 50, "y": 0}, {"id": 9, "x": 40, "y": 0}, {"id": 14, "x": 20, "y": 0}, {"id": 15, "x": 10, "y": 0}]], "end_coord": [[{"id": 3, "x": 80, "y": 10}, {"id": 7, "x": 60, "y": 10}, {"id": 8, "x": 50, "y": 10}, {"id": 9, "x": 40, "y": 10}, {"id": 14, "x": 20, "y": 10}, {"id": 15, "x": 5, "y": 10}]], "id": 1, "begin_time": 1270.326337286374, "end_time": 1334.0882235579445}, {"type": "deactivate", "row_id": [0], "col_id": [0, 1, 2, 3, 4, 5], "id": 2, "begin_time": 1334.0882235579445, "end_time": 1349.0882235579445}], "begin_time": 1255.326337286374, "end_time": 1349.0882235579445}, {"type": "rearrangeJob", "id": 7, "aod_id": 1, "aod_qubits": [2, 7, 8, 12, 14, 15], "begin_locs": [[2, 0, 0, 13], [7, 0, 0, 12], [8, 0, 0, 10], [12, 0, 0, 0], [14, 0, 0, 4], [15, 0, 0, 1]], "end_locs": [[2, 1, 0, 8], [7, 1, 0, 5], [8, 1, 0, 2], [12, 1, 0, 0], [14, 1, 0, 1], [15, 2, 0, 0]], "dependency": {"qubit": [0, 1, 6], "site": [6], "aod": 6}, "insts": [{"type": "activate", "row_id": [0], "row_y": [10], "row_loc": [[0, 0]], "col_id": [5, 4, 3, 0, 2, 1], "col_x": [65, 60, 50, 0, 20, 5], "col_loc": [[0, 13], [0, 12], [0, 10], [0, 0], [0, 4], [0, 1]], "id": 0, "begin_time": 1349.0882235579445, "end_time": 1364.0882235579445}, {"type": "move:big", "move_type": "big", "row_id": [0], "row_y_begin": [10], "row_y_end": [0], "row_loc_begin": [[0, 0]], "row_loc_end": [[1, 0]], "col_id": [5, 4, 3, 0, 2, 1], "col_x_begin": [65, 60, 50, 0, 20, 5], "col_x_end": [80, 50, 20, 0, 10, 2], "col_loc_begin": [[0, 13], [0, 12], [0, 10], [0, 0], [0, 4], [0, 1]], "col_loc_end": [[1, 8], [1, 5], [1, 2], [1, 0], [1, 1], [2, 0]], "begin_coord": [[{"id": 2, "x": 65, "y": 10}, {"id": 7, "x": 60, "y": 10}, {"id": 8, "x": 50, "y": 10}, {"id": 12, "x": 0, "y": 10}, {"id": 14, "x": 20, "y": 10}, {"id": 15, "x": 5, "y": 10}]], "end_coord": [[{"id": 2, "x": 80, "y": 0}, {"id": 7, "x": 50, "y": 0}, {"id": 8, "x": 20, "y": 0}, {"id": 12, "x": 0, "y": 0}, {"id": 14, "x": 10, "y": 0}, {"id": 15, "x": 2, "y": 0}]], "id": 1, "begin_time": 1364.0882235579445, "end_time": 1471.322506749102}, {"type": "deactivate", "row_id": [0], "col_id": [0, 1, 2, 3, 4, 5], "id": 2, "begin_time": 1471.322506749102, "end_time": 1486.322506749102}], "begin_time": 1349.0882235579445, "end_time": 1486.322506749102}, {"type": "rearrangeJob", "id": 8, "aod_id": 1, "aod_qubits": [1], "begin_locs": [[1, 0, 0, 14]], "end_locs": [[1, 1, 0, 6]], "dependency": {"qubit": [1], "site": [6], "aod": 7}, "insts": [{"type": "activate", "row_id": [0], "row_y": [10], "row_loc": [[0, 0]], "col_id": [0], "col_x": [70], "col_loc": [[0, 14]], "id": 0, "begin_time": 1486.322506749102, "end_time": 1501.322506749102}, {"type": "move:big", "move_type": "big", "row_id": [0], "row_y_begin": [10], "row_y_end": [0], "row_loc_begin": [[0, 0]], "row_loc_end": [[1, 0]], "col_id": [0], "col_x_begin": [70], "col_x_end": [60], "col_loc_begin": [[0, 14]], "col_loc_end": [[1, 6]], "begin_coord": [[{"id": 1, "x": 70, "y": 10}]], "end_coord": [[{"id": 1, "x": 60, "y": 0}]], "id": 1, "begin_time": 1501.322506749102, "end_time": 1573.0343939942848}, {"type": "deactivate", "row_id": [0], "col_id": [0], "id": 2, "begin_time": 1573.0343939942848, "end_time": 1588.0343939942848}], "begin_time": 1486.322506749102, "end_time": 1588.0343939942848}, {"type": "rearrangeJob", "id": 9, "aod_id": 0, "aod_qubits": [3], "begin_locs": [[3, 0, 0, 16]], "end_locs": [[3, 1, 0, 4]], "dependency": {"qubit": [6], "site": [6], "aod": 2}, "insts": [{"type": "activate", "row_id": [0], "row_y": [10], "row_loc": [[0, 0]], "col_id": [0], "col_x": [80], "col_loc": [[0, 16]], "id": 0, "begin_time": 1349.0882235579445, "end_time": 1364.0882235579445}, {"type": "move:big", "move_type": "big", "row_id": [0], "row_y_begin": [10], "row_y_end": [0], "row_loc_begin": [[0, 0]], "row_loc_end": [[1, 0]], "col_id": [0], "col_x_begin": [80], "col_x_end": [40], "col_loc_begin": [[0, 16]], "col_loc_end": [[1, 4]], "begin_coord": [[{"id": 3, "x": 80, "y": 10}]], "end_coord": [[{"id": 3, "x": 40, "y": 0}]], "id": 1, "begin_time": 1364.0882235579445, "end_time": 1486.5345847365536}, {"type": "deactivate", "row_id": [0], "col_id": [0], "id": 2, "begin_time": 1486.5345847365536, "end_time": 1501.5345847365536}], "begin_time": 1349.0882235579445, "end_time": 1501.5345847365536}, {"type": "rydberg", "id": 10, "zone_id": 0, "gates": [{"id": 1, "q0": 0, "q1": 2}, {"id": 3, "q0": 1, "q1": 4}, {"id": 5, "q0": 5, "q1": 7}, {"id": 9, "q0": 3, "q1": 6}, {"id": 11, "q0": 8, "q1": 10}, {"id": 17, "q0": 11, "q1": 14}, {"id": 18, "q0": 12, "q1": 15}], "dependency": {"qubit": [4, 5, 7, 8, 9], "rydberg": 4}, "begin_time": 1588.0343939942848, "end_time": 1588.3943939942847}, {"type": "1qGate", "unitary": "u3", "id": 11, "locs": [[0, 2, 0, 8], [1, 1, 0, 6], [4, 2, 0, 6], [5, 2, 0, 5], [7, 1, 0, 5], [3, 1, 0, 4], [8, 1, 0, 2], [11, 2, 0, 1], [12, 1, 0, 0], [15, 2, 0, 0]], "gates": [{"name": "u3", "q": 0, "params": [1.5707963267948966, 0.0, 0.0]}, {"name": "u3", "q": 1, "params": [4.71238898038469, 0.0, 0.0]}, {"name": "u3", "q": 4, "params": [1.5707963267948966, 0.0, 0.0]}, {"name": "u3", "q": 5, "params": [3.141592653589793, 0.0, 0.0]}, {"name": "u3", "q": 7, "params": [1.5707963267948966, 0.0, 0.0]}, {"name": "u3", "q": 3, "params": [1.5707963267948966, 0.0, 0.0]}, {"name": "u3", "q": 8, "params": [3.141592653589793, 0.0, 0.0]}, {"name": "u3", "q": 11, "params": [3.141592653589793, 0.0, 0.0]}, {"name": "u3", "q": 12, "params": [3.141592653589793, 0.0, 0.0]}, {"name": "u3", "q": 15, "params": [1.5707963267948966, 3.141592653589793, 0.0]}], "dependency": {"qubit": [10]}, "params_for_all_qubits": [[1.5707963267948966, 0.0, 0.0], [4.71238898038469, 0.0, 0.0], [1.5707963267948966, 0.0, 0.0], [3.141592653589793, 0.0, 0.0], [1.5707963267948966, 0.0, 0.0], [1.5707963267948966, 0.0, 0.0], [3.141592653589793, 0.0, 0.0], [3.141592653589793, 0.0, 0.0], [3.141592653589793, 0.0, 0.0], [1.5707963267948966, 3.141592653589793, 0.0]], "begin_time": 1588.3943939942847, "end_time": 2108.3943939942847}, {"type": "rearrangeJob", "id": 12, "aod_id": 0, "aod_qubits": [0, 1, 3, 4, 5, 7, 8, 12, 14, 15], "begin_locs": [[0, 2, 0, 8], [1, 1, 0, 6], [3, 1, 0, 4], [4, 2, 0, 6], [5, 2, 0, 5], [7, 1, 0, 5], [8, 1, 0, 2], [12, 1, 0, 0], [14, 1, 0, 1], [15, 2, 0, 0]], "end_locs": [[0, 0, 0, 16], [1, 0, 0, 12], [3, 0, 0, 9], [4, 0, 0, 13], [5, 0, 0, 11], [7, 0, 0, 10], [8, 0, 0, 4], [12, 0, 0, 0], [14, 0, 0, 3], [15, 0, 0, 1]], "dependency": {"qubit": [10, 11], "site": [9, 2, 3, 7], "aod": 9}, "insts": [{"type": "activate", "row_id": [0], "row_y": [0], "row_loc": [[2, 0]], "col_id": [9, 7, 4, 8, 6, 5, 3, 0, 2, 1], "col_x": [82, 60, 40, 62, 52, 50, 20, 0, 10, 2], "col_loc": [[2, 8], [1, 6], [1, 4], [2, 6], [2, 5], [1, 5], [1, 2], [1, 0], [1, 1], [2, 0]], "id": 0, "begin_time": 2108.3943939942847, "end_time": 2123.3943939942847}, {"type": "move:big", "move_type": "big", "row_id": [0], "row_y_begin": [0], "row_y_end": [10], "row_loc_begin": [[2, 0]], "row_loc_end": [[0, 0]], "col_id": [9, 7, 4, 8, 6, 5, 3, 0, 2, 1], "col_x_begin": [82, 60, 40, 62, 52, 50, 20, 0, 10, 2], "col_x_end": [80, 60, 45, 65, 55, 50, 20, 0, 15, 5], "col_loc_begin": [[2, 8], [1, 6], [1, 4], [2, 6], [2, 5], [1, 5], [1, 2], [1, 0], [1, 1], [2, 0]], "col_loc_end": [[0, 16], [0, 12], [0, 9], [0, 13], [0, 11], [0, 10], [0, 4], [0, 0], [0, 3], [0, 1]], "begin_coord": [[{"id": 0, "x": 82, "y": 0}, {"id": 1, "x": 60, "y": 0}, {"id": 3, "x": 40, "y": 0}, {"id": 4, "x": 62, "y": 0}, {"id": 5, "x": 52, "y": 0}, {"id": 7, "x": 50, "y": 0}, {"id": 8, "x": 20, "y": 0}, {"id": 12, "x": 0, "y": 0}, {"id": 14, "x": 10, "y": 0}, {"id": 15, "x": 2, "y": 0}]], "end_coord": [[{"id": 0, "x": 80, "y": 10}, {"id": 1, "x": 60, "y": 10}, {"id": 3, "x": 45, "y": 10}, {"id": 4, "x": 65, "y": 10}, {"id": 5, "x": 55, "y": 10}, {"id": 7, "x": 50, "y": 10}, {"id": 8, "x": 20, "y": 10}, {"id": 12, "x": 0, "y": 10}, {"id": 14, "x": 15, "y": 10}, {"id": 15, "x": 5, "y": 10}]], "id": 1, "begin_time": 2123.3943939942847, "end_time": 2187.1562802658555}, {"type": "deactivate", "row_id": [0], "col_id": [0, 1, 2, 3, 4, 5, 6, 7, 8, 9], "id": 2, "begin_time": 2187.1562802658555, "end_time": 2202.1562802658555}], "begin_time": 2108.3943939942847, "end_time": 2202.1562802658555}, {"type": "rearrangeJob", "id": 13, "aod_id": 1, "aod_qubits": [13, 5], "begin_locs": [[13, 0, 0, 7], [5, 0, 0, 11]], "end_locs": [[13, 1, 0, 2], [5, 2, 0, 8]], "dependency": {"qubit": [1, 12], "site": [12], "aod": 15}, "insts": [{"type": "activate", "row_id": [0], "row_y": [10], "row_loc": [[0, 0]], "col_id": [0, 1], "col_x": [35, 55], "col_loc": [[0, 7], [0, 11]], "id": 0, "begin_time": 2202.1562802658555, "end_time": 2217.1562802658555}, {"type": "move:big", "move_type": "big", "row_id": [0], "row_y_begin": [10], "row_y_end": [0], "row_loc_begin": [[0, 0]], "row_loc_end": [[1, 0]], "col_id": [0, 1], "col_x_begin": [35, 55], "col_x_end": [20, 82], "col_loc_begin": [[0, 7], [0, 11]], "col_loc_end": [[1, 2], [2, 8]], "begin_coord": [[{"id": 13, "x": 35, "y": 10}, {"id": 5, "x": 55, "y": 10}]], "end_coord": [[{"id": 13, "x": 20, "y": 0}, {"id": 5, "x": 82, "y": 0}]], "id": 1, "begin_time": 2217.1562802658555, "end_time": 2319.4790496110213}, {"type": "deactivate", "row_id": [0], "col_id": [0, 1], "id": 2, "begin_time": 2319.4790496110213, "end_time": 2334.4790496110213}], "begin_time": 2202.1562802658555, "end_time": 2334.4790496110213}, {"type": "rearrangeJob", "id": 14, "aod_id": 0, "aod_qubits": [8, 16, 14], "begin_locs": [[8, 0, 0, 4], [16, 0, 0, 2], [14, 0, 0, 3]], "end_locs": [[8, 1, 0, 4], [16, 1, 0, 3], [14, 2, 0, 3]], "dependency": {"qubit": [1, 12], "site": [12], "aod": 12}, "insts": [{"type": "activate", "row_id": [0], "row_y": [10], "row_loc": [[0, 0]], "col_id": [2, 0, 1], "col_x": [20, 10, 15], "col_loc": [[0, 4], [0, 2], [0, 3]], "id": 0, "begin_time": 2202.1562802658555, "end_time": 2217.1562802658555}, {"type": "move:big", "move_type": "big", "row_id": [0], "row_y_begin": [10], "row_y_end": [0], "row_loc_begin": [[0, 0]], "row_loc_end": [[1, 0]], "col_id": [2, 0, 1], "col_x_begin": [20, 10, 15], "col_x_end": [40, 30, 32], "col_loc_begin": [[0, 4], [0, 2], [0, 3]], "col_loc_end": [[1, 4], [1, 3], [2, 3]], "begin_coord": [[{"id": 8, "x": 20, "y": 10}, {"id": 16, "x": 10, "y": 10}, {"id": 14, "x": 15, "y": 10}]], "end_coord": [[{"id": 8, "x": 40, "y": 0}, {"id": 16, "x": 30, "y": 0}, {"id": 14, "x": 32, "y": 0}]], "id": 1, "begin_time": 2217.1562802658555, "end_time": 2307.3292045936014}, {"type": "deactivate", "row_id": [0], "col_id": [0, 1, 2], "id": 2, "begin_time": 2307.3292045936014, "end_time": 2322.3292045936014}], "begin_time": 2202.1562802658555, "end_time": 2322.3292045936014}, {"type": "rearrangeJob", "id": 15, "aod_id": 1, "aod_qubits": [9], "begin_locs": [[9, 0, 0, 8]], "end_locs": [[9, 1, 0, 1]], "dependency": {"qubit": [6], "site": [12], "aod": 8}, "insts": [{"type": "activate", "row_id": [0], "row_y": [10], "row_loc": [[0, 0]], "col_id": [0], "col_x": [40], "col_loc": [[0, 8]], "id": 0, "begin_time": 2001.160110803127, "end_time": 2016.160110803127}, {"type": "move:big", "move_type": "big", "row_id": [0], "row_y_begin": [10], "row_y_end": [0], "row_loc_begin": [[0, 0]], "row_loc_end": [[1, 0]], "col_id": [0], "col_x_begin": [40], "col_x_end": [10], "col_loc_begin": [[0, 8]], "col_loc_end": [[1, 1]], "begin_coord": [[{"id": 9, "x": 40, "y": 10}]], "end_coord": [[{"id": 9, "x": 10, "y": 0}]], "id": 1, "begin_time": 2016.160110803127, "end_time": 2123.3943939942847}, {"type": "deactivate", "row_id": [0], "col_id": [0], "id": 2, "begin_time": 2123.3943939942847, "end_time": 2138.3943939942847}], "begin_time": 2001.160110803127, "end_time": 2138.3943939942847}, {"type": "rydberg", "id": 16, "zone_id": 0, "gates": [{"id": 6, "q0": 2, "q1": 5}, {"id": 12, "q0": 10, "q1": 13}, {"id": 14, "q0": 6, "q1": 8}, {"id": 19, "q0": 9, "q1": 11}, {"id": 22, "q0": 14, "q1": 16}], "dependency": {"qubit": [10, 11, 13, 14, 15], "rydberg": 10}, "begin_time": 2334.4790496110213, "end_time": 2334.8390496110214}, {"type": "1qGate", "unitary": "u3", "id": 17, "locs": [[2, 1, 0, 8], [10, 2, 0, 2], [13, 1, 0, 2], [6, 2, 0, 4], [8, 1, 0, 4], [9, 1, 0, 1], [14, 2, 0, 3]], "gates": [{"name": "u3", "q": 2, "params": [1.5707963267948966, 0.0, 3.141592653589793]}, {"name": "u3", "q": 10, "params": [0.0, 1.5707963267948966, 1.5707963267948966]}, {"name": "u3", "q": 13, "params": [1.5707963267948966, 3.141592653589793, 3.141592653589793]}, {"name": "u3", "q": 6, "params": [0.0, 1.5707963267948966, 1.5707963267948966]}, {"name": "u3", "q": 8, "params": [1.5707963267948966, 3.141592653589793, 3.141592653589793]}, {"name": "u3", "q": 9, "params": [1.5707963267948966, 0.0, 3.141592653589793]}, {"name": "u3", "q": 14, "params": [0.0, 1.5707963267948966, 1.5707963267948966]}], "dependency": {"qubit": [16]}, "params_for_all_qubits": [[1.5707963267948966, 0.0, 3.141592653589793], [0.0, 1.5707963267948966, 1.5707963267948966], [1.5707963267948966, 3.141592653589793, 3.141592653589793], [0.0, 1.5707963267948966, 1.5707963267948966], [1.5707963267948966, 3.141592653589793, 3.141592653589793], [1.5707963267948966, 0.0, 3.141592653589793], [0.0, 1.5707963267948966, 1.5707963267948966]], "begin_time": 2334.8390496110214, "end_time": 2698.8390496110214}, {"type": "rearrangeJob", "id": 18, "aod_id": 0, "aod_qubits": [2, 8, 9, 13, 14], "begin_locs": [[2, 1, 0, 8], [8, 1, 0, 4], [9, 1, 0, 1], [13, 1, 0, 2], [14, 2, 0, 3]], "end_locs": [[2, 0, 0, 15], [8, 0, 0, 8], [9, 0, 0, 2], [13, 0, 0, 4], [14, 0, 0, 6]], "dependency": {"qubit": [17], "site": [2, 3, 14, 15], "aod": 14}, "insts": [{"type": "activate", "row_id": [0], "row_y": [0], "row_loc": [[1, 0]], "col_id": [4, 3, 0, 1, 2], "col_x": [80, 40, 10, 20, 32], "col_loc": [[1, 8], [1, 4], [1, 1], [1, 2], [2, 3]], "id": 0, "begin_time": 2698.8390496110214, "end_time": 2713.8390496110214}, {"type": "move:big", "move_type": "big", "row_id": [0], "row_y_begin": [0], "row_y_end": [10], "row_loc_begin": [[1, 0]], "row_loc_end": [[0, 0]], "col_id": [4, 3, 0, 1, 2], "col_x_begin": [80, 40, 10, 20, 32], "col_x_end": [75, 40, 10, 20, 30], "col_loc_begin": [[1, 8], [1, 4], [1, 1], [1, 2], [2, 3]], "col_loc_end": [[0, 15], [0, 8], [0, 2], [0, 4], [0, 6]], "begin_coord": [[{"id": 2, "x": 80, "y": 0}, {"id": 8, "x": 40, "y": 0}, {"id": 9, "x": 10, "y": 0}, {"id": 13, "x": 20, "y": 0}, {"id": 14, "x": 32, "y": 0}]], "end_coord": [[{"id": 2, "x": 75, "y": 10}, {"id": 8, "x": 40, "y": 10}, {"id": 9, "x": 10, "y": 10}, {"id": 13, "x": 20, "y": 10}, {"id": 14, "x": 30, "y": 10}]], "id": 1, "begin_time": 2713.8390496110214, "end_time": 2777.6009358825922}, {"type": "deactivate", "row_id": [0], "col_id": [0, 1, 2, 3, 4], "id": 2, "begin_time": 2777.6009358825922, "end_time": 2792.6009358825922}], "begin_time": 2698.8390496110214, "end_time": 2792.6009358825922}, {"type": "rearrangeJob", "id": 19, "aod_id": 0, "aod_qubits": [1, 7, 8, 9, 12], "begin_locs": [[1, 0, 0, 12], [7, 0, 0, 10], [8, 0, 0, 8], [9, 0, 0, 2], [12, 0, 0, 0]], "end_locs": [[1, 1, 0, 8], [7, 1, 0, 2], [8, 1, 0, 1], [9, 2, 0, 0], [12, 1, 0, 0]], "dependency": {"qubit": [18, 12], "site": [18, 12], "aod": 18}, "insts": [{"type": "activate", "row_id": [0], "row_y": [10], "row_loc": [[0, 0]], "col_id": [4, 3, 2, 1, 0], "col_x": [60, 50, 40, 10, 0], "col_loc": [[0, 12], [0, 10], [0, 8], [0, 2], [0, 0]], "id": 0, "begin_time": 2792.6009358825922, "end_time": 2807.6009358825922}, {"type": "move:big", "move_type": "big", "row_id": [0], "row_y_begin": [10], "row_y_end": [0], "row_loc_begin": [[0, 0]], "row_loc_end": [[1, 0]], "col_id": [4, 3, 2, 1, 0], "col_x_begin": [60, 50, 40, 10, 0], "col_x_end": [80, 20, 10, 2, 0], "col_loc_begin": [[0, 12], [0, 10], [0, 8], [0, 2], [0, 0]], "col_loc_end": [[1, 8], [1, 2], [1, 1], [2, 0], [1, 0]], "begin_coord": [[{"id": 1, "x": 60, "y": 10}, {"id": 7, "x": 50, "y": 10}, {"id": 8, "x": 40, "y": 10}, {"id": 9, "x": 10, "y": 10}, {"id": 12, "x": 0, "y": 10}]], "end_coord": [[{"id": 1, "x": 80, "y": 0}, {"id": 7, "x": 20, "y": 0}, {"id": 8, "x": 10, "y": 0}, {"id": 9, "x": 2, "y": 0}, {"id": 12, "x": 0, "y": 0}]], "id": 1, "begin_time": 2807.6009358825922, "end_time": 2914.8352190737496}, {"type": "deactivate", "row_id": [0], "col_id": [0, 1, 2, 3, 4], "id": 2, "begin_time": 2914.8352190737496, "end_time": 2929.8352190737496}], "begin_time": 2792.6009358825922, "end_time": 2929.8352190737496}, {"type": "rearrangeJob", "id": 20, "aod_id": 1, "aod_qubits": [2, 13], "begin_locs": [[2, 0, 0, 15], [13, 0, 0, 4]], "end_locs": [[2, 1, 0, 4], [13, 2, 0, 3]], "dependency": {"qubit": [18], "site": [18], "aod": 13}, "insts": [{"type": "activate", "row_id": [0], "row_y": [10], "row_loc": [[0, 0]], "col_id": [1, 0], "col_x": [75, 20], "col_loc": [[0, 15], [0, 4]], "id": 0, "begin_time": 2792.6009358825922, "end_time": 2807.6009358825922}, {"type": "move:big", "move_type": "big", "row_id": [0], "row_y_begin": [10], "row_y_end": [0], "row_loc_begin": [[0, 0]], "row_loc_end": [[1, 0]], "col_id": [1, 0], "col_x_begin": [75, 20], "col_x_end": [40, 32], "col_loc_begin": [[0, 15], [0, 4]], "col_loc_end": [[1, 4], [2, 3]], "begin_coord": [[{"id": 2, "x": 75, "y": 10}, {"id": 13, "x": 20, "y": 10}]], "end_coord": [[{"id": 2, "x": 40, "y": 0}, {"id": 13, "x": 32, "y": 0}]], "id": 1, "begin_time": 2807.6009358825922, "end_time": 2922.6512007021724}, {"type": "deactivate", "row_id": [0], "col_id": [0, 1], "id": 2, "begin_time": 2922.6512007021724, "end_time": 2937.6512007021724}], "begin_time": 2792.6009358825922, "end_time": 2937.6512007021724}, {"type": "rydberg", "id": 21, "zone_id": 0, "gates": [{"id": 7, "q0": 1, "q1": 5}, {"id": 13, "q0": 7, "q1": 10}, {"id": 15, "q0": 2, "q1": 6}, {"id": 20, "q0": 8, "q1": 11}, {"id": 21, "q0": 9, "q1": 12}, {"id": 23, "q0": 13, "q1": 16}], "dependency": {"qubit": [16, 17, 19, 20], "rydberg": 16}, "begin_time": 2937.6512007021724, "end_time": 2938.0112007021726}, {"type": "1qGate", "unitary": "u3", "id": 22, "locs": [[1, 1, 0, 8], [5, 2, 0, 8], [10, 2, 0, 2], [7, 1, 0, 2], [2, 1, 0, 4], [6, 2, 0, 4], [11, 2, 0, 1], [8, 1, 0, 1], [12, 1, 0, 0], [9, 2, 0, 0], [13, 2, 0, 3], [16, 1, 0, 3]], "gates": [{"name": "u3", "q": 1, "params": [0.0, 1.5707963267948966, 1.5707963267948966]}, {"name": "u3", "q": 5, "params": [1.5707963267948966, 3.141592653589793, 3.141592653589793]}, {"name": "u3", "q": 10, "params": [1.5707963267948966, 0.0, 0.0]}, {"name": "u3", "q": 7, "params": [4.71238898038469, 0.0, 0.0]}, {"name": "u3", "q": 2, "params": [4.71238898038469, 0.0, 0.0]}, {"name": "u3", "q": 6, "params": [1.5707963267948966, 0.0, 0.0]}, {"name": "u3", "q": 11, "params": [1.5707963267948966, 3.141592653589793, 3.141592653589793]}, {"name": "u3", "q": 8, "params": [0.0, 1.5707963267948966, 1.5707963267948966]}, {"name": "u3", "q": 12, "params": [1.5707963267948966, 0.0, 0.0]}, {"name": "u3", "q": 9, "params": [4.71238898038469, 0.0, 0.0]}, {"name": "u3", "q": 13, "params": [0.0, 1.5707963267948966, 1.5707963267948966]}, {"name": "u3", "q": 16, "params": [1.5707963267948966, 3.141592653589793, 3.141592653589793]}], "dependency": {"qubit": [21]}, "params_for_all_qubits": [[0.0, 1.5707963267948966, 1.5707963267948966], [1.5707963267948966, 3.141592653589793, 3.141592653589793], [1.5707963267948966, 0.0, 0.0], [4.71238898038469, 0.0, 0.0], [4.71238898038469, 0.0, 0.0], [1.5707963267948966, 0.0, 0.0], [1.5707963267948966, 3.141592653589793, 3.141592653589793], [0.0, 1.5707963267948966, 1.5707963267948966], [1.5707963267948966, 0.0, 0.0], [4.71238898038469, 0.0, 0.0], [0.0, 1.5707963267948966, 1.5707963267948966], [1.5707963267948966, 3.141592653589793, 3.141592653589793]], "begin_time": 2938.0112007021726, "end_time": 3562.0112007021726}, {"type": "rearrangeJob", "id": 23, "aod_id": 0, "aod_qubits": [1, 5, 7, 8, 9, 10, 11, 12], "begin_locs": [[1, 1, 0, 8], [5, 2, 0, 8], [7, 1, 0, 2], [8, 1, 0, 1], [9, 2, 0, 0], [10, 2, 0, 2], [11, 2, 0, 1], [12, 1, 0, 0]], "end_locs": [[1, 0, 0, 15], [5, 0, 0, 17], [7, 0, 0, 5], [8, 0, 0, 3], [9, 0, 0, 2], [10, 0, 0, 12], [11, 0, 0, 4], [12, 0, 0, 0]], "dependency": {"qubit": [22], "site": [2, 19, 20, 14], "aod": 19}, "insts": [{"type": "activate", "row_id": [0], "row_y": [0], "row_loc": [[1, 0]], "col_id": [6, 7, 4, 2, 1, 5, 3, 0], "col_x": [80, 82, 20, 10, 2, 22, 12, 0], "col_loc": [[1, 8], [2, 8], [1, 2], [1, 1], [2, 0], [2, 2], [2, 1], [1, 0]], "id": 0, "begin_time": 3562.0112007021726, "end_time": 3577.0112007021726}, {"type": "move:big", "move_type": "big", "row_id": [0], "row_y_begin": [0], "row_y_end": [10], "row_loc_begin": [[1, 0]], "row_loc_end": [[0, 0]], "col_id": [6, 7, 4, 2, 1, 5, 3, 0], "col_x_begin": [80, 82, 20, 10, 2, 22, 12, 0], "col_x_end": [75, 85, 25, 15, 10, 60, 20, 0], "col_loc_begin": [[1, 8], [2, 8], [1, 2], [1, 1], [2, 0], [2, 2], [2, 1], [1, 0]], "col_loc_end": [[0, 15], [0, 17], [0, 5], [0, 3], [0, 2], [0, 12], [0, 4], [0, 0]], "begin_coord": [[{"id": 1, "x": 80, "y": 0}, {"id": 5, "x": 82, "y": 0}, {"id": 7, "x": 20, "y": 0}, {"id": 8, "x": 10, "y": 0}, {"id": 9, "x": 2, "y": 0}, {"id": 10, "x": 22, "y": 0}, {"id": 11, "x": 12, "y": 0}, {"id": 12, "x": 0, "y": 0}]], "end_coord": [[{"id": 1, "x": 75, "y": 10}, {"id": 5, "x": 85, "y": 10}, {"id": 7, "x": 25, "y": 10}, {"id": 8, "x": 15, "y": 10}, {"id": 9, "x": 10, "y": 10}, {"id": 10, "x": 60, "y": 10}, {"id": 11, "x": 20, "y": 10}, {"id": 12, "x": 0, "y": 10}]], "id": 1, "begin_time": 3577.0112007021726, "end_time": 3696.546308376981}, {"type": "deactivate", "row_id": [0], "col_id": [0, 1, 2, 3, 4, 5, 6, 7], "id": 2, "begin_time": 3696.546308376981, "end_time": 3711.546308376981}], "begin_time": 3562.0112007021726, "end_time": 3711.546308376981}, {"type": "rearrangeJob", "id": 24, "aod_id": 1, "aod_qubits": [16, 2, 13, 6], "begin_locs": [[16, 1, 0, 3], [2, 1, 0, 4], [13, 2, 0, 3], [6, 2, 0, 4]], "end_locs": [[16, 0, 0, 7], [2, 0, 0, 10], [13, 0, 0, 8], [6, 0, 0, 11]], "dependency": {"qubit": [22], "site": [19, 13], "aod": 20}, "insts": [{"type": "activate", "row_id": [0], "row_y": [0], "row_loc": [[1, 0]], "col_id": [0, 2, 1, 3], "col_x": [30, 40, 32, 42], "col_loc": [[1, 3], [1, 4], [2, 3], [2, 4]], "id": 0, "begin_time": 3562.0112007021726, "end_time": 3577.0112007021726}, {"type": "move:big", "move_type": "big", "row_id": [0], "row_y_begin": [0], "row_y_end": [10], "row_loc_begin": [[1, 0]], "row_loc_end": [[0, 0]], "col_id": [0, 2, 1, 3], "col_x_begin": [30, 40, 32, 42], "col_x_end": [35, 50, 40, 55], "col_loc_begin": [[1, 3], [1, 4], [2, 3], [2, 4]], "col_loc_end": [[0, 7], [0, 10], [0, 8], [0, 11]], "begin_coord": [[{"id": 16, "x": 30, "y": 0}, {"id": 2, "x": 40, "y": 0}, {"id": 13, "x": 32, "y": 0}, {"id": 6, "x": 42, "y": 0}]], "end_coord": [[{"id": 16, "x": 35, "y": 10}, {"id": 2, "x": 50, "y": 10}, {"id": 13, "x": 40, "y": 10}, {"id": 6, "x": 55, "y": 10}]], "id": 1, "begin_time": 3577.0112007021726, "end_time": 3654.238655704456}, {"type": "deactivate", "row_id": [0], "col_id": [0, 1, 2, 3], "id": 2, "begin_time": 3654.238655704456, "end_time": 3669.238655704456}], "begin_time": 3562.0112007021726, "end_time": 3669.238655704456}], "runtime": 3711.546308376981}